garpix_auth/MANIFEST.in
garpix_auth/README.rst
garpix_auth/__init__.py
garpix_auth/apps.py
garpix_auth/settings.py
garpix_auth/setup.py
garpix_auth/urls.py
garpix_auth/views.py
garpix_auth/__pycache__/__init__.cpython-38.pyc
garpix_auth/__pycache__/apps.cpython-38.pyc
garpix_auth/__pycache__/urls.cpython-38.pyc
garpix_auth/__pycache__/views.cpython-38.pyc
garpix_auth/forms/__init__.py
garpix_auth/forms/login.py
garpix_auth/forms/__pycache__/__init__.cpython-38.pyc
garpix_auth/forms/__pycache__/login.cpython-38.pyc
garpix_auth/models/__init__.py
garpix_auth/models/access_token.py
garpix_auth/models/backend.py
garpix_auth/models/refresh_token.py
garpix_auth/models/__pycache__/__init__.cpython-38.pyc
garpix_auth/models/__pycache__/access_token.cpython-38.pyc
garpix_auth/models/__pycache__/backend.cpython-38.pyc
garpix_auth/models/__pycache__/refresh_token.cpython-38.pyc
garpix_auth/rest/auth_token_serializer.py
garpix_auth/rest/authentication.py
garpix_auth/rest/logout_view.py
garpix_auth/rest/obtain_auth_token.py
garpix_auth/rest/refresh_token_serializer.py
garpix_auth/rest/refresh_token_view.py
garpix_auth/rest/utils.py
garpix_auth/rest/__pycache__/auth_token_serializer.cpython-38.pyc
garpix_auth/rest/__pycache__/authentication.cpython-38.pyc
garpix_auth/rest/__pycache__/logout_view.cpython-38.pyc
garpix_auth/rest/__pycache__/obtain_auth_token.cpython-38.pyc
garpix_auth/rest/__pycache__/refresh_token_serializer.cpython-38.pyc
garpix_auth/rest/__pycache__/refresh_token_view.cpython-38.pyc
garpix_auth/rest/__pycache__/utils.cpython-38.pyc
garpix_auth/tests/__init__.py
garpix_auth/tests/test_api.py
garpix_auth/tests/test_views.py
garpix_auth-2.4.0.dist-info/METADATA
garpix_auth-2.4.0.dist-info/WHEEL
garpix_auth-2.4.0.dist-info/top_level.txt
garpix_auth-2.4.0.dist-info/RECORD
