Metadata-Version: 2.1
Name: garpix-auth
Version: 2.4.0
Author: Garpix LTD
Author-email: info@garpix.com
License: MIT
Classifier: Development Status :: 4 - Beta
Classifier: Environment :: Web Environment
Classifier: Intended Audience :: Developers
Classifier: License :: OSI Approved :: MIT License
Classifier: Operating System :: OS Independent
Classifier: Programming Language :: Python
Classifier: Framework :: Django
Classifier: Programming Language :: Python :: 3.6
Classifier: Programming Language :: Python :: 3.7
Classifier: Programming Language :: Python :: 3.8
Requires-Dist: Django (>=1.11)
Requires-Dist: djangorestframework (>=3.8)
Requires-Dist: django-oauth-toolkit (>=1.1.2)
Requires-Dist: social-auth-app-django (>=2.1.0)
Requires-Dist: django-rest-framework-social-oauth2 (>=1.1.0)
